[
  {
    "id": 24,
    "type": "text",
    "title": "<p style=\"--invalid:0in;--invalid:normal\"><b>Introduction to this Session</b></p>",
    "text": "<p style=\"--invalid:0in;--invalid:normal\"><span style=\"--invalid:12.0pt\">Read thoughtfully these passages about sin. Try to become a character in the Genesis stories. Imagine yourself in the garden of Eden, on Noah’s ark, or helping to build the tower of Babel. Notice that in Jeremiah the prophet grieves over the sins of a whole society. In 2 Samuel the prophet Nathan throws a blinding spotlight on David’s sin. Psalm 51 is a confession of sin that could be your own.</span></p><p style=\"--invalid:0in;--invalid:normal\"><span style=\"--invalid:12.0pt\"><br></span></p>",
    "audio": "https://beadisciple-guest.s3.us-east-1.amazonaws.com/DFT%20I%20Session%202%20Audio/Voice%20Over%20files/03%20S2D1A.mp3"
  }
]